aiotrenergy/__init__.py
aiotrenergy/client/__init__.py
aiotrenergy/client/account.py
aiotrenergy/client/aml.py
aiotrenergy/client/client.py
aiotrenergy/client/consumers.py
aiotrenergy/enums.py
aiotrenergy/exceptions.py
aiotrenergy/objects/__init__.py
aiotrenergy/objects/account.py
aiotrenergy/objects/address_report.py
aiotrenergy/objects/aml.py
aiotrenergy/objects/base.py
aiotrenergy/objects/consumer.py
aiotrenergy/objects/consumer_blockchain_energy.py
aiotrenergy/objects/consumers_summary.py
aiotrenergy/objects/consumption_stat.py
aiotrenergy/objects/top_up_data.py
aiotrenergy/objects/wallet.py
aiotrenergy/requests/__init__.py
aiotrenergy/requests/account/__init__.py
aiotrenergy/requests/account/show.py
aiotrenergy/requests/account/top_up.py
aiotrenergy/requests/aml/__init__.py
aiotrenergy/requests/aml/create.py
aiotrenergy/requests/aml/index.py
aiotrenergy/requests/base.py
aiotrenergy/requests/consumers/__init__.py
aiotrenergy/requests/consumers/activate.py
aiotrenergy/requests/consumers/activate_address.py
aiotrenergy/requests/consumers/address_report.py
aiotrenergy/requests/consumers/consumer_blockchain_energy.py
aiotrenergy/requests/consumers/consumers_summary.py
aiotrenergy/requests/consumers/consumption_stats.py
aiotrenergy/requests/consumers/create.py
aiotrenergy/requests/consumers/deactivate.py
aiotrenergy/requests/consumers/destroy.py
aiotrenergy/requests/consumers/index.py
aiotrenergy/requests/consumers/mass_top_up_trx.py
aiotrenergy/requests/consumers/reset_order_validity.py
aiotrenergy/requests/consumers/show.py
aiotrenergy/requests/consumers/store_delayed_consumers.py
aiotrenergy/requests/consumers/toggle_auto_renewal.py
aiotrenergy/requests/consumers/update.py
aiotrenergy/requests/pagination.py
aiotrenergy/requests/params.py
aiotrenergy/responses/__init__.py
aiotrenergy/responses/account/__init__.py
aiotrenergy/responses/account/show.py
aiotrenergy/responses/account/top_up.py
aiotrenergy/responses/aml/__init__.py
aiotrenergy/responses/aml/create.py
aiotrenergy-0.0.6.dist-info/LICENSE
aiotrenergy-0.0.6.dist-info/METADATA
aiotrenergy-0.0.6.dist-info/WHEEL
aiotrenergy-0.0.6.dist-info/RECORD
