Metadata-Version: 2.1
Name: aiotrenergy
Version: 0.0.6
Summary: Async python wrapper for tr.energy api
Author: drforse
Author-email: george.lifeslice@gmail.com
Requires-Python: >=3.10,<4.0
Classifier: Programming Language :: Python :: 3
Classifier: Programming Language :: Python :: 3.10
Classifier: Programming Language :: Python :: 3.11
Classifier: Programming Language :: Python :: 3.12
Requires-Dist: httpx[http2] (>=0.28.1,<0.29.0)
Requires-Dist: pydantic (>=2.10.6,<3.0.0)
Project-URL: homepage, https://github.com/drforse/aiotrenergy
Project-URL: repository, https://github.com/drforse/aiotrenergy
